logging_azure/__init__.py
logging_azure/configuration.py
logging_azure/handler.py
logging_azure/log_record.py
logging_azure/log_service.py
logging_azure/service_provider.py
logging_azure-1.0.2.dist-info/LICENSE
logging_azure-1.0.2.dist-info/METADATA
logging_azure-1.0.2.dist-info/WHEEL
logging_azure-1.0.2.dist-info/top_level.txt
logging_azure-1.0.2.dist-info/RECORD
