Metadata-Version: 2.1
Name: logging-azure
Version: 1.0.2
Summary: A python async logging handler and service extension for Azure Log Workspace OMS.
Home-page: https://github.com/matchawine/logging-azure
Author: Joshua Logan
Author-email: joshua@matcha.wine
License: GPL
Keywords: utils
Platform: UNKNOWN
Classifier: Development Status :: 5 - Production/Stable
Classifier: Environment :: Plugins
Classifier: Intended Audience :: Developers
Classifier: License :: OSI Approved :: GNU General Public License (GPL)
Classifier: Operating System :: OS Independent
Classifier: Natural Language :: English
Classifier: Programming Language :: Python :: 3.7
Classifier: Topic :: Software Development :: Libraries :: Python Modules
Requires-Python: >=3.7
Requires-Dist: injector (>=0.18.2)
Requires-Dist: cython (>=0.29.14)
Requires-Dist: grequests (>=0.4.0)
